{
    "api": {
        "type": "gallery/four-col",
        "data": []
    },
    "examples": [
        {
            "title": "",
            "example": {
                "type":"gallery/four-col",
                "container_padding":"section layout",
                "internal_theme":"theme--white",
                "data":[ 
                  { 
                    "type":"type/h2",
                    "data":"About us"
                  },
                  "Technology has allowed cool blokes to participate in the global conversation of bung stubbies. The next Generation of heaps good sad guys have already skived off over at the tinny house. "
                ],
                "gallery":[
                  {
                    "img":
                      {
                        "src":"/images/placeholders/ph1.jpg",
                        "alt":"alt tag"
                      }
                    ,
                    "title": "Mr Coolio",
                    "caption":"I'm cool "
                  },
                  {
                    "img":
                      {
                        "src":"/images/placeholders/ph2.jpg",
                        "alt":"alt tag"
                      }
                    ,
                    "title": "Mr Doppy",
                    "caption":"I'm dopey"
                  },
                  {
                    "img":
                      {
                        "src":"/images/placeholders/ph3.jpg",
                        "alt":"alt tag"
                      }
                    ,
                    "title": "Mr Sleepy",
                    "caption":"I'm sleepy "
                  },
                  {
                    "img":
                      {
                        "src":"/images/placeholders/ph4.jpg",
                        "alt":"alt tag"
                      }
                    ,
                    "title": "Mr Sneezy",
                    "caption":"I'm sneezy"
                  }

                ]
            }
            
        }
    ]
}