{
    "api": {
        "type": "form/field--number",
        "placeholder": "placeholder text",
        "label": "Field label",
        "field_note": "",
        "errors": []
    },
    "examples": [
        {
            "title": "Number input",
            "notes":"Use this for input fields that should contain a numeric value. On a touchscreen device the number keys will show by default when the field is focused.",
            "example": {
                "type": "form/field--number",
                "name": "licence_version",
                "label": "Driver licence version",
                "field_note": "Item 5B on your driver licence",
                "maxlength": "3",
                "placeholder": "e.g. 123"
            }
        },
        {
            "title": "Number input with an error state",
            "example": {
                "type": "form/field--number",
                "name": "licence_version",
                "label": "Driver licence version",
                "field_note": "Item 5B on your driver licence",
                "maxlength": "3",
                "placeholder": "eg 123",
                 "errors": [
                    {
                        "msg": "Ooops, there was an error"
                    }
                ]
            }
        }
    ]
}


